[
  {
    "Position": 1,
    "Name": "The Sisterhood of the Traveling Pants",
    "Year": 2005
  },
  {
    "Position": 2,
    "Name": "Palm Springs",
    "Year": 2020
  },
  {
    "Position": 3,
    "Name": "Adventureland",
    "Year": 2009
  },
  {
    "Position": 4,
    "Name": "The Spectacular Now",
    "Year": 2013
  },
  {
    "Position": 5,
    "Name": "She's the Man",
    "Year": 2006
  },
  {
    "Position": 6,
    "Name": "The Kings of Summer",
    "Year": 2013
  },
  {
    "Position": 7,
    "Name": "Call Me by Your Name",
    "Year": 2017
  },
  {
    "Position": 8,
    "Name": "Mamma Mia!",
    "Year": 2008
  },
  {
    "Position": 9,
    "Name": "Aquamarine",
    "Year": 2006
  },
  {
    "Position": 10,
    "Name": "Luca",
    "Year": 2021
  },
  {
    "Position": 11,
    "Name": "My Old Ass",
    "Year": 2024
  },
  {
    "Position": 12,
    "Name": "Theater Camp",
    "Year": 2023
  },
  {
    "Position": 13,
    "Name": "Moonrise Kingdom",
    "Year": 2012
  },
  {
    "Position": 14,
    "Name": "The Way Way Back",
    "Year": 2013
  },
  {
    "Position": 15,
    "Name": "The To Do List",
    "Year": 2013
  }
]